best_download/__init__.py
best_download-0.1.1.dist-info/LICENSE
best_download-0.1.1.dist-info/METADATA
best_download-0.1.1.dist-info/WHEEL
best_download-0.1.1.dist-info/top_level.txt
best_download-0.1.1.dist-info/RECORD
