Metadata-Version: 2.1
Name: best-download
Version: 0.1.1
Summary: URL downloader supporting checkpointing and continuous checksumming.
Home-page: https://github.com/EleutherAI/best-download
Author: researcher2
Author-email: 2researcher2@gmail.com
Classifier: Programming Language :: Python :: 3
Classifier: License :: OSI Approved :: MIT License
Classifier: Operating System :: OS Independent
Requires-Python: >=3.6
License-File: LICENSE
Requires-Dist: requests
Requires-Dist: rehash
Requires-Dist: tqdm
Provides-Extra: dev
Requires-Dist: twine ; extra == 'dev'
Requires-Dist: pytest ; extra == 'dev'
Requires-Dist: flask ; extra == 'dev'
